cowpilot/__init__.py
cowpilot/cli.py
cowpilot-0.1.0.dist-info/METADATA
cowpilot-0.1.0.dist-info/WHEEL
cowpilot-0.1.0.dist-info/entry_points.txt
cowpilot-0.1.0.dist-info/licenses/LICENSE
cowpilot-0.1.0.dist-info/RECORD
