Metadata-Version: 2.4
Name: cowpilot
Version: 0.1.0
Summary: A cow copliot for your terminal
License-File: LICENSE
Requires-Python: >=3.10
Requires-Dist: openai>=1.61.1
